{
  "target": "table7",
  "current_attempt": 20,
  "best_score": 93,
  "best_attempt": 11,
  "status": "max_attempts_reached",
  "total_duration_seconds": 3853,
  "attempts": [
    {"attempt": 1, "score": 55, "duration_seconds": 128},
    {"attempt": 2, "score": 58, "duration_seconds": 143},
    {"attempt": 3, "score": 55, "duration_seconds": 205},
    {"attempt": 4, "score": 62, "duration_seconds": 114},
    {"attempt": 5, "score": 62, "duration_seconds": 953},
    {"attempt": 6, "score": 62, "duration_seconds": 358},
    {"attempt": 7, "score": 60, "duration_seconds": 217},
    {"attempt": 8, "score": 84, "duration_seconds": 255},
    {"attempt": 9, "score": 84, "duration_seconds": 297},
    {"attempt": 10, "score": 84, "duration_seconds": 197},
    {"attempt": 11, "score": 93, "duration_seconds": 224},
    {"attempt": 12, "score": 93, "duration_seconds": 190},
    {"attempt": 13, "score": 93, "duration_seconds": 14},
    {"attempt": 14, "score": 93, "duration_seconds": 99},
    {"attempt": 15, "score": 93, "duration_seconds": 89},
    {"attempt": 16, "score": 93, "duration_seconds": 56},
    {"attempt": 17, "score": 93, "duration_seconds": 46},
    {"attempt": 18, "score": 93, "duration_seconds": 41},
    {"attempt": 19, "score": 93, "duration_seconds": 64},
    {"attempt": 20, "score": 93, "duration_seconds": 4}
  ]
}
